{"job_id": "b57cac0be4e942188dba0becffe838ca", "transcribed_text": "hello world this is a demo of speech to sign language conversion thank you", "sign_sequence": [{"word": "hello", "image_url": "https://media.giphy.com/media/26gspjl5bxzhSdJtK/giphy.gif", "type": "real_gif"}, {"word": "world", "image_url": "https://via.placeholder.com/200x200/2196F3/white?text=WORLD", "type": "placeholder"}, {"word": "this", "image_url": "https://via.placeholder.com/200x200/9E9E9E/white?text=THIS", "type": "placeholder"}, {"word": "is", "image_url": "https://via.placeholder.com/200x200/9E9E9E/white?text=IS", "type": "placeholder"}, {"word": "a", "image_url": "https://via.placeholder.com/200x200/9E9E9E/white?text=A", "type": "placeholder"}, {"word": "demo", "image_url": "https://via.placeholder.com/200x200/673AB7/white?text=DEMO", "type": "placeholder"}, {"word": "of", "image_url": "https://via.placeholder.com/200x200/9E9E9E/white?text=OF", "type": "placeholder"}, {"word": "speech", "image_url": "https://via.placeholder.com/200x200/9E9E9E/white?text=SPEECH", "type": "placeholder"}, {"word": "to", "image_url": "https://via.placeholder.com/200x200/9E9E9E/white?text=TO", "type": "placeholder"}, {"word": "sign", "image_url": "https://via.placeholder.com/200x200/9E9E9E/white?text=SIGN", "type": "placeholder"}, {"word": "language", "image_url": "https://via.placeholder.com/200x200/9E9E9E/white?text=LANGUAGE", "type": "placeholder"}, {"word": "conversion", "image_url": "https://via.placeholder.com/200x200/9E9E9E/white?text=CONVERSION", "type": "placeholder"}, {"word": "thank", "image_url": "https://media.giphy.com/media/3o7abKhOpu0NwenH3O/giphy.gif", "type": "real_gif"}, {"word": "you", "image_url": "https://media.giphy.com/media/l1J9u3TZfpmeDLkD6/giphy.gif", "type": "real_gif"}], "status": "completed"}